LICENSE
MANIFEST.in
README.rst
setup.cfg
setup.py
django_rest_allauth/__init__.py
django_rest_allauth/admin.py
django_rest_allauth/apps.py
django_rest_allauth/models.py
django_rest_allauth/tests.py
django_rest_allauth/views.py
django_rest_allauth.egg-info/PKG-INFO
django_rest_allauth.egg-info/SOURCES.txt
django_rest_allauth.egg-info/dependency_links.txt
django_rest_allauth.egg-info/top_level.txt
django_rest_allauth/api/__init__.py
django_rest_allauth/api/serializers.py
django_rest_allauth/api/urls.py
django_rest_allauth/api/views.py
django_rest_allauth/migrations/0001_initial.py
django_rest_allauth/migrations/0002_auto_20201124_0823.py
django_rest_allauth/migrations/0003_auto_20201124_1450.py
django_rest_allauth/migrations/__init__.py